bonsait/__init__.py
bonsait/cache.py
bonsait/configs.py
bonsait/connector.py
bonsait/core.py
bonsait/models.py
bonsait/utils/__init__.py
bonsait/utils/similarity_func.py
bonsait-0.1.5.dist-info/LICENSE
bonsait-0.1.5.dist-info/METADATA
bonsait-0.1.5.dist-info/WHEEL
bonsait-0.1.5.dist-info/RECORD
